docker_image/__init__.py
docker_image/digest.py
docker_image/reference.py
docker_image/regexp.py
docker_image_py-0.1.13.dist-info/LICENSE
docker_image_py-0.1.13.dist-info/METADATA
docker_image_py-0.1.13.dist-info/WHEEL
docker_image_py-0.1.13.dist-info/top_level.txt
docker_image_py-0.1.13.dist-info/RECORD
